README.md
setup.py
influx_neptuneapex/__init__.py
influx_neptuneapex/__main__.py
influx_neptuneapex.egg-info/PKG-INFO
influx_neptuneapex.egg-info/SOURCES.txt
influx_neptuneapex.egg-info/dependency_links.txt
influx_neptuneapex.egg-info/entry_points.txt
influx_neptuneapex.egg-info/requires.txt
influx_neptuneapex.egg-info/top_level.txt