Metadata-Version: 2.1
Name: influx-neptuneapex
Version: 1.0
Summary: Feed data from a neptune apex into an InfluxDB
Home-page: https://github.com/garbled1/influx_neptuneapex
Author: Tim Rightnour
Author-email: thegarbledone@gmail.com
License: GPL
Project-URL: Gitub Repo, https://github.com/garbled1/influx_neptuneapex
Platform: UNKNOWN
Requires-Python: >3.5
